{"cameraMode":{"drawMode":0,"name":"Shaded","section":"Shading Mode"},"sceneLighting":true,"audioPlay":false,"sceneViewState":{"showFog":true,"showMaterialUpdate":false,"showSkybox":true,"showFlares":true,"showImageEffects":true,"showParticleSystems":true},"in2DMode":false,"pivot":{"x":282.2607116699219,"y":15.522812843322754,"z":1099.086669921875},"rotation":{"x":-0.08968104422092438,"y":0.4515145719051361,"z":-0.0456719771027565,"w":-0.8865698575973511},"size":1.0295960903167725,"orthographic":false}